{"trial_id": "10", "hyperparameters": {"space": [{"class_name": "Choice", "config": {"name": "max_norm_1", "default": 3.0, "conditions": [], "values": [3.0, 3.25, 3.5, 3.75, 4.0], "ordered": true}}, {"class_name": "Choice", "config": {"name": "max_norm_2", "default": 3.0, "conditions": [], "values": [3.0, 3.25, 3.5, 3.75, 4.0], "ordered": true}}, {"class_name": "Choice", "config": {"name": "max_norm_3", "default": 3.0, "conditions": [], "values": [3.0, 3.25, 3.5, 3.75, 4.0], "ordered": true}}, {"class_name": "Choice", "config": {"name": "max_norm_4", "default": 3.0, "conditions": [], "values": [3.0, 3.25, 3.5, 3.75, 4.0], "ordered": true}}], "values": {"max_norm_1": 3.5, "max_norm_2": 4.0, "max_norm_3": 3.0, "max_norm_4": 3.25}}, "metrics": {"metrics": {"loss": {"direction": "min", "observations": [{"value": [0.19895625114440918], "step": 11}]}, "accuracy": {"direction": "max", "observations": [{"value": [0.9396462440490723], "step": 11}]}, "val_loss": {"direction": "min", "observations": [{"value": [0.23913416266441345], "step": 11}]}, "val_accuracy": {"direction": "max", "observations": [{"value": [0.9355000257492065], "step": 11}]}}}, "score": 0.9355000257492065, "best_step": 11, "status": "COMPLETED", "message": null}