{"trial_id": "10", "hyperparameters": {"space": [{"class_name": "Choice", "config": {"name": "rate_1", "default": 4, "conditions": [], "values": [4, 8, 16], "ordered": true}}, {"class_name": "Choice", "config": {"name": "rate_2", "default": 8, "conditions": [], "values": [8, 16, 32], "ordered": true}}, {"class_name": "Choice", "config": {"name": "rate_3", "default": 16, "conditions": [], "values": [16, 32, 64], "ordered": true}}, {"class_name": "Choice", "config": {"name": "rate_4", "default": 4, "conditions": [], "values": [4, 8, 16], "ordered": true}}, {"class_name": "Choice", "config": {"name": "rate_5", "default": 32, "conditions": [], "values": [32, 64, 128], "ordered": true}}], "values": {"rate_1": 16, "rate_2": 8, "rate_3": 32, "rate_4": 4, "rate_5": 128}}, "metrics": {"metrics": {"loss": {"direction": "min", "observations": [{"value": [0.44911840558052063], "step": 24}]}, "accuracy": {"direction": "max", "observations": [{"value": [0.8661511540412903], "step": 24}]}, "val_loss": {"direction": "min", "observations": [{"value": [0.35716870427131653], "step": 24}]}, "val_accuracy": {"direction": "max", "observations": [{"value": [0.8955000042915344], "step": 24}]}}}, "score": 0.8955000042915344, "best_step": 24, "status": "COMPLETED", "message": null}