{"trial_id": "12", "hyperparameters": {"space": [{"class_name": "Choice", "config": {"name": "rate_1", "default": 0.25, "conditions": [], "values": [0.25, 0.5, 0.75], "ordered": true}}, {"class_name": "Choice", "config": {"name": "rate_2", "default": 0.25, "conditions": [], "values": [0.25, 0.5, 0.75], "ordered": true}}, {"class_name": "Choice", "config": {"name": "rate_3", "default": 0.25, "conditions": [], "values": [0.25, 0.5, 0.75], "ordered": true}}, {"class_name": "Choice", "config": {"name": "rate_4", "default": 0.25, "conditions": [], "values": [0.25, 0.5, 0.75], "ordered": true}}, {"class_name": "Choice", "config": {"name": "rate_5", "default": 0.25, "conditions": [], "values": [0.25, 0.5, 0.75], "ordered": true}}], "values": {"rate_1": 0.5, "rate_2": 0.75, "rate_3": 0.25, "rate_4": 0.75, "rate_5": 0.25}}, "metrics": {"metrics": {"loss": {"direction": "min", "observations": [{"value": [0.8519279360771179], "step": 8}]}, "accuracy": {"direction": "max", "observations": [{"value": [0.7335784435272217], "step": 8}]}, "val_loss": {"direction": "min", "observations": [{"value": [0.701190173625946], "step": 8}]}, "val_accuracy": {"direction": "max", "observations": [{"value": [0.8134999871253967], "step": 8}]}}}, "score": 0.8134999871253967, "best_step": 8, "status": "COMPLETED", "message": null}